grader_labextension/__init__.py
grader_labextension/api_handler.py
grader_labextension/registry.py
grader_labextension/api/__init__.py
grader_labextension/api/typing_utils.py
grader_labextension/api/util.py
grader_labextension/api/models/__init__.py
grader_labextension/api/models/assignment.py
grader_labextension/api/models/assignment_detail.py
grader_labextension/api/models/assignment_settings.py
grader_labextension/api/models/auto_status.py
grader_labextension/api/models/base_model.py
grader_labextension/api/models/error_message.py
grader_labextension/api/models/feedback_status.py
grader_labextension/api/models/lecture.py
grader_labextension/api/models/manual_status.py
grader_labextension/api/models/remote_file_status.py
grader_labextension/api/models/submission.py
grader_labextension/api/models/submission_period.py
grader_labextension/api/models/user.py
grader_labextension/api/models/user_submissions_inner.py
grader_labextension/handlers/__init__.py
grader_labextension/handlers/assignment.py
grader_labextension/handlers/base_handler.py
grader_labextension/handlers/config.py
grader_labextension/handlers/grading.py
grader_labextension/handlers/lectures.py
grader_labextension/handlers/permission.py
grader_labextension/handlers/submissions.py
grader_labextension/handlers/version_control.py
grader_labextension/services/__init__.py
grader_labextension/services/git.py
grader_labextension/services/request.py
grader_labextension/tests/__init__.py
grader_labextension/tests/test_handlers.py
grader_labextension-0.10.0.data/data/etc/jupyter/jupyter_server_config.d/grader_labextension.json
grader_labextension-0.10.0.data/data/share/jupyter/labextensions/grader-labextension/package.json
grader_labextension-0.10.0.data/data/share/jupyter/labextensions/grader-labextension/schemas/grader-labextension/package.json.orig
grader_labextension-0.10.0.data/data/share/jupyter/labextensions/grader-labextension/schemas/grader-labextension/plugin.json
grader_labextension-0.10.0.dist-info/METADATA
grader_labextension-0.10.0.dist-info/WHEEL
grader_labextension-0.10.0.dist-info/licenses/LICENSE
grader_labextension-0.10.0.dist-info/RECORD
