Metadata-Version: 2.4
Name: grader-labextension
Version: 0.10.0
Summary: Grader Labextension is a JupyterLab extension to enable automatic grading of assignment notebooks.
Project-URL: Homepage, https://github.com/TU-Wien-dataLAB/grader-labextension
Project-URL: Bug Tracker, https://github.com/TU-Wien-dataLAB/grader-labextension/issues
Project-URL: Repository, https://github.com/TU-Wien-dataLAB/grader-labextension.git
Author-email: "Florian Jaeger, Matthias Matt" <datalab@tuwien.ac.at>
License: BSD 3-Clause License
License-File: LICENSE
Keywords: jupyter,jupyterlab,jupyterlab-extension
Classifier: Framework :: Jupyter
Classifier: Framework :: Jupyter :: JupyterLab
Classifier: Framework :: Jupyter :: JupyterLab :: 4
Classifier: Framework :: Jupyter :: JupyterLab :: Extensions
Classifier: Framework :: Jupyter :: JupyterLab :: Extensions :: Prebuilt
Classifier: License :: OSI Approved :: BSD License
Classifier: Programming Language :: Python
Classifier: Programming Language :: Python :: 3
Classifier: Programming Language :: Python :: 3.9
Classifier: Programming Language :: Python :: 3.10
Classifier: Programming Language :: Python :: 3.11
Classifier: Programming Language :: Python :: 3.12
Classifier: Programming Language :: Python :: 3.13
Requires-Python: >=3.9
Requires-Dist: grader-service>=0.10.0
Requires-Dist: jupyter-server<3,>=2.4.0
Provides-Extra: test
Requires-Dist: coverage; extra == 'test'
Requires-Dist: pytest; extra == 'test'
Requires-Dist: pytest-asyncio; extra == 'test'
Requires-Dist: pytest-cov; extra == 'test'
Requires-Dist: pytest-jupyter[server]>=0.6.0; extra == 'test'
